dft_aim_siepic_laser_pic_project1/DFT.xml
dft_aim_siepic_laser_pic_project1/__init__.py
dft_aim_siepic_laser_pic_project1-0.1.1.dist-info/licenses/LICENSE
dft_aim_siepic_laser_pic_project1-0.1.1.dist-info/licenses/LICENSE.md
dft_aim_siepic_laser_pic_project1-0.1.1.dist-info/METADATA
dft_aim_siepic_laser_pic_project1-0.1.1.dist-info/WHEEL
dft_aim_siepic_laser_pic_project1-0.1.1.dist-info/top_level.txt
dft_aim_siepic_laser_pic_project1-0.1.1.dist-info/RECORD
