Metadata-Version: 2.4
Name: dft_aim_siepic_laser_pic_project1
Version: 0.1.1
Summary: Design for Test rules for the AIM-SiEPIC Laser Integration Silicon Photonics course, Project 1, using the SiEPIC_EBeam_PDK process design kit (PDK) for silicon photonics fabrication.
Author-email: Lukas Chrostowski <lukasc@ece.ubc.ca>
Project-URL: Homepage, https://github.com/SiEPIC/DFT_AIM_SiEPIC_Laser_PIC_Project1
Project-URL: Issues, https://github.com/SiEPIC/DFT_AIM_SiEPIC_Laser_PIC_Project1/issues
Classifier: Programming Language :: Python :: 3
Classifier: License :: OSI Approved :: MIT License
Classifier: Operating System :: OS Independent
Requires-Python: >=3.8
License-File: LICENSE
License-File: LICENSE.md
Dynamic: license-file
